gnnepcsaft/__init__.py
gnnepcsaft/configs/__init__.py
gnnepcsaft/configs/configs_parallel.py
gnnepcsaft/configs/default.py
gnnepcsaft/configs/default_assoc.py
gnnepcsaft/configs/gatv2_assoc.py
gnnepcsaft/configs/gatv2_assoc_2.py
gnnepcsaft/configs/gatv2_assoc_3.py
gnnepcsaft/configs/gatv2_msigmae.py
gnnepcsaft/configs/gatv2_msigmae_2.py
gnnepcsaft/configs/gatv2_msigmae_3.py
gnnepcsaft/configs/gatv2_msigmae_4.py
gnnepcsaft/configs/habitch_msigmae.py
gnnepcsaft/configs/pna_assoc_2.py
gnnepcsaft/configs/pna_assoc_3.py
gnnepcsaft/configs/pna_msigmae.py
gnnepcsaft/configs/pna_msigmae_2.py
gnnepcsaft/configs/pna_msigmae_3.py
gnnepcsaft/configs/pna_msigmae_4.py
gnnepcsaft/configs/pna_msigmae_5.py
gnnepcsaft/configs/pna_msigmae_6.py
gnnepcsaft/configs/pna_msigmae_6_1.py
gnnepcsaft/configs/pna_msigmae_7.py
gnnepcsaft/configs/search_space.py
gnnepcsaft/configs/transformer_msigmae.py
gnnepcsaft/configs/transformer_msigmae_2.py
gnnepcsaft/data/.gitignore
gnnepcsaft/data/__init__.py
gnnepcsaft/data/dft.py
gnnepcsaft/data/esper2023/raw/SI_pcp-saft_parameters.csv
gnnepcsaft/data/esper2023.dvc
gnnepcsaft/data/gc_pcsaft/readme.txt
gnnepcsaft/data/gc_pcsaft/rehner2023_hetero.json
gnnepcsaft/data/gc_pcsaft/rehner2023_homo.json
gnnepcsaft/data/gc_pcsaft/sauer2014_hetero.json
gnnepcsaft/data/gc_pcsaft/sauer2014_homo.json
gnnepcsaft/data/gc_pcsaft/sauer2014_smarts.json
gnnepcsaft/data/graph.py
gnnepcsaft/data/graphdataset.py
gnnepcsaft/data/molfamily.py
gnnepcsaft/data/ogb_utils.py
gnnepcsaft/data/preprocess.py
gnnepcsaft/data/ramirez2022/raw/RAMIREZ2022.csv
gnnepcsaft/data/ramirez2022/raw/RAMIREZ2022_original.csv
gnnepcsaft/data/ramirez2022/raw/data.parquet
gnnepcsaft/data/ramirez2022.dvc
gnnepcsaft/data/rdkit_util.py
gnnepcsaft/data/thermoml/raw/binary.parquet
gnnepcsaft/data/thermoml/raw/co2_binary.parquet
gnnepcsaft/data/thermoml/raw/co2_ternary.parquet
gnnepcsaft/data/thermoml/raw/lle_binary.parquet
gnnepcsaft/data/thermoml/raw/lle_binary_temp.parquet
gnnepcsaft-0.3.1.dist-info/METADATA
gnnepcsaft-0.3.1.dist-info/WHEEL
gnnepcsaft-0.3.1.dist-info/licenses/LICENSE
gnnepcsaft-0.3.1.dist-info/RECORD
