Metadata-Version: 2.4
Name: gnnepcsaft
Version: 0.3.1
Summary: GNNPCSAFT Project.
License: GNU
License-File: LICENSE
Author: Wildson Lima
Requires-Python: >=3.10
Classifier: License :: Other/Proprietary License
Classifier: Programming Language :: Python :: 3
Classifier: Programming Language :: Python :: 3.10
Classifier: Programming Language :: Python :: 3.11
Classifier: Programming Language :: Python :: 3.12
Classifier: Programming Language :: Python :: 3.13
Classifier: Programming Language :: Python :: 3.14
Requires-Dist: feos (>=0.8.0,<0.9.0)
Requires-Dist: numpy (>=2.2.4,<3.0.0)
Requires-Dist: rdkit (>=2024.9.6,<2025.0.0)
Requires-Dist: si-units (>=0.11.0,<0.12.0)
